torchpal/__init__.py
torchpal/__init__.pyi
torchpal/_config/__init__.py
torchpal/_config/_constants.py
torchpal/da/__init__.py
torchpal/da/__init__.pyi
torchpal/da/_da.py
torchpal/data/__init__.py
torchpal/data/__init__.pyi
torchpal/data/_data.py
torchpal/train/__init__.py
torchpal/train/__init__.pyi
torchpal/train/_train.py
torchpal/utils/__init__.py
torchpal/utils/__init__.pyi
torchpal/utils/_utils.py
torchpal-0.1.1.dist-info/licenses/LICENSE
torchpal-0.1.1.dist-info/METADATA
torchpal-0.1.1.dist-info/WHEEL
torchpal-0.1.1.dist-info/top_level.txt
torchpal-0.1.1.dist-info/RECORD
