Metadata-Version: 2.4
Name: torchpal
Version: 0.1.1
Summary: PyTorch辅助工具包：极度新手友好的 PyTorch 伴侣
Author: 2bitbit
License-Expression: MIT
Project-URL: Homepage, https://github.com/2bitbit/torchpal/
Project-URL: Bug Tracker, https://github.com/2bitbit/torchpal/issues/
Classifier: Programming Language :: Python :: 3
Classifier: Operating System :: OS Independent
Classifier: Topic :: Scientific/Engineering :: Artificial Intelligence
Requires-Python: >=3.10
License-File: LICENSE
Requires-Dist: ipython>=8.12.3
Requires-Dist: matplotlib>=3.10.3
Requires-Dist: matplotlib_inline>=0.1.7
Requires-Dist: pandas>=2.2.3
Requires-Dist: Pillow>=11.2.1
Requires-Dist: scikit_learn>=1.6.1
Requires-Dist: torch>=2.6.0
Requires-Dist: torchvision>=0.21.0
Dynamic: license-file
Dynamic: requires-dist
